{
  "Logistic Regression": {
    "accuracy": 0.8254,
    "f1_score": 0.7442,
    "precision": 0.7273,
    "recall": 0.7619,
    "auc_roc": 0.8685,
    "cv_f1_mean": 0.6073,
    "cv_f1_std": 0.1099,
    "train_time_seconds": 0.0206,
    "carbon_emissions_kg": 0.001118,
    "energy_kwh": 1.994e-05,
    "n_parameters": 19
  },
  "Decision Tree": {
    "accuracy": 0.7778,
    "f1_score": 0.6818,
    "precision": 0.6522,
    "recall": 0.7143,
    "auc_roc": 0.7647,
    "cv_f1_mean": 0.5245,
    "cv_f1_std": 0.072,
    "train_time_seconds": 0.007,
    "carbon_emissions_kg": 0.00115,
    "energy_kwh": 2.052e-05,
    "n_parameters": 43
  },
  "Random Forest": {
    "accuracy": 0.8413,
    "f1_score": 0.75,
    "precision": 0.7895,
    "recall": 0.7143,
    "auc_roc": 0.881,
    "cv_f1_mean": 0.5109,
    "cv_f1_std": 0.078,
    "train_time_seconds": 0.108,
    "carbon_emissions_kg": 0.000634,
    "energy_kwh": 1.132e-05,
    "n_parameters": 6478
  },
  "XGBoost": {
    "accuracy": 0.8413,
    "f1_score": 0.7619,
    "precision": 0.7619,
    "recall": 0.7619,
    "auc_roc": 0.8866,
    "cv_f1_mean": 0.5613,
    "cv_f1_std": 0.0711,
    "train_time_seconds": 0.2611,
    "carbon_emissions_kg": 0.001431,
    "energy_kwh": 2.553e-05,
    "n_parameters": 5000
  }
}